masterdata/__init__.py
masterdata/admin.py
masterdata/check.py
masterdata/importing/__init__.py
masterdata/importing/modelimporter.py
masterdata/issuecount.py
masterdata/issuetuple.py
masterdata/migrations/0001_initial.py
masterdata/migrations/__init__.py
masterdata/modelregistry.py
masterdata/models.py
masterdata/registry.py
masterdata/templates/admin/change_list.html
masterdata/templates/admin/change_list_object_tools.html
masterdata/templates/masterdata/filter.html
masterdata/templates/masterdata/import_confirm.html
masterdata/templates/masterdata/import_form.html
masterdata/views/__init__.py
masterdata/views/importview.py
django_masterdata-0.1.1.dist-info/WHEEL
django_masterdata-0.1.1.dist-info/METADATA
django_masterdata-0.1.1.dist-info/RECORD
